[
  {
    "text": "a lot of flavor i'm gonna go back home",
    "start": 181.04,
    "duration": 8.0
  },
  {
    "text": "i'm gonna open up a camel burger shop",
    "start": 184.72,
    "duration": 4.32
  },
  {
    "text": "tastes beautiful tastes really nice try",
    "start": 189.519,
    "duration": 4.321
  },
  {
    "text": "it i promise you we all like it and you",
    "start": 191.76,
    "duration": 3.759
  },
  {
    "text": "will come back again",
    "start": 193.84,
    "duration": 4.72
  }
]